azure/mgmt/azurestack/__init__.py
azure/mgmt/azurestack/_azure_stack_management_client.py
azure/mgmt/azurestack/_configuration.py
azure/mgmt/azurestack/_version.py
azure/mgmt/azurestack/aio/__init__.py
azure/mgmt/azurestack/aio/_azure_stack_management_client.py
azure/mgmt/azurestack/aio/_configuration.py
azure/mgmt/azurestack/aio/operations/__init__.py
azure/mgmt/azurestack/aio/operations/_cloud_manifest_file_operations.py
azure/mgmt/azurestack/aio/operations/_customer_subscriptions_operations.py
azure/mgmt/azurestack/aio/operations/_linked_subscriptions_operations.py
azure/mgmt/azurestack/aio/operations/_operations.py
azure/mgmt/azurestack/aio/operations/_products_operations.py
azure/mgmt/azurestack/aio/operations/_registrations_operations.py
azure/mgmt/azurestack/models/__init__.py
azure/mgmt/azurestack/models/_azure_stack_management_client_enums.py
azure/mgmt/azurestack/models/_models.py
azure/mgmt/azurestack/models/_models_py3.py
azure/mgmt/azurestack/operations/__init__.py
azure/mgmt/azurestack/operations/_cloud_manifest_file_operations.py
azure/mgmt/azurestack/operations/_customer_subscriptions_operations.py
azure/mgmt/azurestack/operations/_linked_subscriptions_operations.py
azure/mgmt/azurestack/operations/_operations.py
azure/mgmt/azurestack/operations/_products_operations.py
azure/mgmt/azurestack/operations/_registrations_operations.py
azure_mgmt_azurestack-1.0.0.dist-info/METADATA
azure_mgmt_azurestack-1.0.0.dist-info/WHEEL
azure_mgmt_azurestack-1.0.0.dist-info/top_level.txt
azure_mgmt_azurestack-1.0.0.dist-info/RECORD
